{
  "CreatedAt": "2024-08-05T05:50:30+0000",
  "DerivedFrom": {
    "Filename": "atoc.zip",
    "SizeBytes": 57677961,
    "SourceUrl": "https://data.atoc.org/system/files/ttis181.zip",
    "SourceDownloadedAt": "2024-08-05T05:34:01+0000",
    "SourceLicence": "CC-BY-2.0",
    "SourceAttribution": "RSP Limited (Rail Delivery Group)",
    "ParochialCacheKey": "43069346b457baf6615025521dcf0cd28838a980"
  },
  "Coverage": {
    "Temporal": {
      "start": "2024-08-05",
      "end": "2024-09-03"
    },
    "Spatial": "Part of Great Britain"
  },
  "ParochialCacheKey": "d5cd192ae38454000c165311afbb3d1fd0de8601"
}
