{
  "CreatedAt": ["2023-09-11T06:54:49+0000"],
  "CreatedWithOpenTripPlannerVersion": ["2.2.0, ser.ver.id: 76, commit: 0e15511b630347df581f1f230de7f470db1b7b26, branch: master"],
  "DerivedFrom": [
    {
      "Filename": ["streetGraph.obj"],
      "SizeBytes": [966312057],
      "CreatedAt": ["2023-09-11T06:06:02+0000"],
      "CreatedWithOpenTripPlannerVersion": ["2.2.0, ser.ver.id: 76, commit: 0e15511b630347df581f1f230de7f470db1b7b26, branch: master"],
      "DerivedFrom": [
        {
          "Filename": ["walesish.osm.pbf"],
          "SizeBytes": [302248358],
          "CreatedAt": ["2023-09-11T05:41:18+0000"],
          "DerivedFrom": {
            "Filename": ["great-britain-latest.osm.pbf"],
            "SizeBytes": [1660763593],
            "SourceUrl": ["https://download.geofabrik.de/europe/great-britain-latest.osm.pbf"],
            "SourceDownloadedAt": ["2023-09-11T05:34:57+0000"],
            "SourceLicence": ["ODbL-1.0"],
            "SourceAttribution": ["OpenStreetMap contributors"],
            "ParochialCacheKey": ["1660c4fd4ed67d2ba5e85fb33e0a21d511f1b593"]
          },
          "ParochialCacheKey": ["1279782365f91943a0608fb3c365f779c171da53"]
        },
        {
          "Filename": ["walesish.terr50.tif"],
          "SizeBytes": [70798519],
          "CreatedAt": ["2023-07-07T11:51:52+0000"],
          "DerivedFrom": {
            "Filename": ["terr50_gagg_gb.zip"],
            "SizeBytes": [161687898],
            "SourceUrl": ["https://api.os.uk/downloads/v1/products/Terrain50/downloads?area=GB&format=ASCII+Grid+and+GML+%28Grid%29&redirect"],
            "SourceDownloadedAt": ["2023-07-07T11:49:11+0000"],
            "SourceLicence": ["OGL-UK-3.0"],
            "SourceAttribution": ["Contains OS data © Crown copyright and database right 2022"],
            "ParochialCacheKey": ["4e0846a2c1d039d5e28346d9431e9afbdcad6e0c"]
          },
          "ParochialCacheKey": ["53231d28014c2a06613084eac16f43420a6520ef"]
        }
      ],
      "ParochialCacheKey": ["6c08bb61622c80b6d0ae1a71ea97d3df853fe337"]
    },
    {
      "Filename": ["merged.walesish.gtfs.zip"],
      "SizeBytes": [92529960],
      "CreatedAt": ["2023-09-11T06:31:08+0000"],
      "DerivedFrom": [
        {
          "Filename": ["NCSD.tnds.walesish.gtfs.zip"],
          "SizeBytes": [36943],
          "CreatedAt": ["2023-09-11T05:43:25+0000"],
          "DerivedFrom": {
            "Filename": ["NCSD.bus.tnds.zip"],
            "SizeBytes": [1560022],
            "SourceUrl": ["ftp://ftp.tnds.basemap.co.uk/NCSD.zip"],
            "SourceDownloadedAt": ["2023-09-11T05:31:17+0000"],
            "SourceLicence": ["OGL-UK-3.0"],
            "SourceAttribution": ["Traveline"],
            "ParochialCacheKey": ["07870cd4abee2b2adc618b672eb2922a72345bf0"]
          },
          "Coverage": {
            "Temporal": {
              "start": ["2023-09-11"],
              "end": ["2023-10-10"]
            },
            "Spatial": ["Part of Great Britain"]
          },
          "ParochialCacheKey": ["a74c49ebe1776cc2942d3aa746a0c76d6a9c73c0"]
        },
        {
          "Filename": ["W.tnds.walesish.gtfs.zip"],
          "SizeBytes": [8129288],
          "CreatedAt": ["2023-09-11T05:40:04+0000"],
          "DerivedFrom": {
            "Filename": ["W.bus.tnds.zip"],
            "SizeBytes": [9197730],
            "SourceUrl": ["ftp://ftp.tnds.basemap.co.uk/W.zip"],
            "SourceDownloadedAt": ["2023-09-11T05:31:13+0000"],
            "SourceLicence": ["OGL-UK-3.0"],
            "SourceAttribution": ["Traveline"],
            "ParochialCacheKey": ["ce789f76ee681699915546ecc9a72cf494ef7b93"]
          },
          "Coverage": {
            "Temporal": {
              "start": ["2023-09-11"],
              "end": ["2023-10-10"]
            },
            "Spatial": ["Part of Great Britain"]
          },
          "ParochialCacheKey": ["9cc4edbd7c329f81f86d65072204edf3e6e1e49a"]
        },
        {
          "Filename": ["atoc.walesish.gtfs.zip"],
          "SizeBytes": [1488764],
          "CreatedAt": ["2023-09-11T06:07:14+0000"],
          "DerivedFrom": {
            "Filename": ["atoc.zip"],
            "SizeBytes": [52644528],
            "SourceUrl": ["https://data.atoc.org/system/files/ttis851.zip"],
            "SourceDownloadedAt": ["2023-09-11T05:33:01+0000"],
            "SourceLicence": ["CC-BY-2.0"],
            "SourceAttribution": ["RSP Limited (Rail Delivery Group)"],
            "ParochialCacheKey": ["a2eaf60cce4a10565408802f2970b8e6f0dc8334"]
          },
          "Coverage": {
            "Temporal": {
              "start": ["2023-09-11"],
              "end": ["2023-10-10"]
            },
            "Spatial": ["Part of Great Britain"]
          },
          "ParochialCacheKey": ["0425ce20a5e1e326a6eef796c39cc249c9181bbd"]
        },
        {
          "Filename": ["north_west.bods.walesish.gtfs.zip"],
          "SizeBytes": [29957514],
          "CreatedAt": ["2023-09-11T05:32:25+0000"],
          "DerivedFrom": {
            "Filename": ["north_west.bods.gtfs.zip"],
            "SizeBytes": [57919817],
            "SourceUrl": ["https://data.bus-data.dft.gov.uk/timetable/download/gtfs-file/north_west/"],
            "SourceDownloadedAt": ["2023-09-11T05:31:32+0000"],
            "SourceLicence": ["OGL-UK-3.0"],
            "SourceAttribution": ["UK Department for Transport"],
            "ParochialCacheKey": ["76dcf63dd6e3317de3c933f5e8c67645e51888df"]
          },
          "Coverage": {
            "Temporal": {
              "start": ["2023-09-11"],
              "end": ["2023-10-10"]
            },
            "Spatial": ["Part of Great Britain"]
          },
          "ParochialCacheKey": ["f0780e7f2e30db2a764708f28368a193c4001b92"]
        },
        {
          "Filename": ["south_west.bods.walesish.gtfs.zip"],
          "SizeBytes": [19876137],
          "CreatedAt": ["2023-09-11T05:33:35+0000"],
          "DerivedFrom": {
            "Filename": ["south_west.bods.gtfs.zip"],
            "SizeBytes": [96254235],
            "SourceUrl": ["https://data.bus-data.dft.gov.uk/timetable/download/gtfs-file/south_west/"],
            "SourceDownloadedAt": ["2023-09-11T05:33:00+0000"],
            "SourceLicence": ["OGL-UK-3.0"],
            "SourceAttribution": ["UK Department for Transport"],
            "ParochialCacheKey": ["c51c94f91a8598c88f5aadfaea16acbddf7d8e2e"]
          },
          "Coverage": {
            "Temporal": {
              "start": ["2023-09-11"],
              "end": ["2023-10-10"]
            },
            "Spatial": ["Part of Great Britain"]
          },
          "ParochialCacheKey": ["108eb92da6885fd7dfdad298af0b401671e44836"]
        },
        {
          "Filename": ["west_midlands.bods.walesish.gtfs.zip"],
          "SizeBytes": [10408155],
          "CreatedAt": ["2023-09-11T05:32:54+0000"],
          "DerivedFrom": {
            "Filename": ["west_midlands.bods.gtfs.zip"],
            "SizeBytes": [46587048],
            "SourceUrl": ["https://data.bus-data.dft.gov.uk/timetable/download/gtfs-file/west_midlands/"],
            "SourceDownloadedAt": ["2023-09-11T05:32:30+0000"],
            "SourceLicence": ["OGL-UK-3.0"],
            "SourceAttribution": ["UK Department for Transport"],
            "ParochialCacheKey": ["ba1f2ced033f4843e7fc9b5caa8132b7adf94a01"]
          },
          "Coverage": {
            "Temporal": {
              "start": ["2023-09-11"],
              "end": ["2023-10-10"]
            },
            "Spatial": ["Part of Great Britain"]
          },
          "ParochialCacheKey": ["5aa590b556eaff1b00b0276aa04288ff7807d467"]
        },
        {
          "Filename": ["walesish.osm.pbf"],
          "SizeBytes": [302248358],
          "CreatedAt": ["2023-09-11T05:41:18+0000"],
          "DerivedFrom": {
            "Filename": ["great-britain-latest.osm.pbf"],
            "SizeBytes": [1660763593],
            "SourceUrl": ["https://download.geofabrik.de/europe/great-britain-latest.osm.pbf"],
            "SourceDownloadedAt": ["2023-09-11T05:34:57+0000"],
            "SourceLicence": ["ODbL-1.0"],
            "SourceAttribution": ["OpenStreetMap contributors"],
            "ParochialCacheKey": ["1660c4fd4ed67d2ba5e85fb33e0a21d511f1b593"]
          },
          "Coverage": {
            "Temporal": {
              "start": {},
              "end": {}
            },
            "Spatial": {}
          },
          "ParochialCacheKey": ["1279782365f91943a0608fb3c365f779c171da53"]
        }
      ],
      "ParochialCacheKey": ["9dca74d07f80bb285569f3fe018aec9d8a248f8d"]
    }
  ],
  "Coverage": {
    "Temporal": {
      "start": ["2023-09-11"],
      "end": ["2023-10-10"]
    },
    "Spatial": ["Part of Great Britain"]
  },
  "ParochialCacheKey": ["3a152dbed852a5860ac4c5ffdbc9c149c36eea6d"]
}
