{
  "CreatedAt": ["2024-09-30T06:37:48+0000"],
  "DerivedFrom": [
    {
      "Filename": ["NCSD.tnds.walesish.gtfs.zip"],
      "SizeBytes": [31022],
      "CreatedAt": ["2024-09-30T05:41:16+0000"],
      "DerivedFrom": {
        "Filename": ["NCSD.bus.tnds.zip"],
        "SizeBytes": [1664617],
        "SourceUrl": ["ftp://ftp.tnds.basemap.co.uk/NCSD.zip"],
        "SourceDownloadedAt": ["2024-09-30T05:37:22+0000"],
        "SourceLicence": ["OGL-UK-3.0"],
        "SourceAttribution": ["Traveline"],
        "ParochialCacheKey": ["df1459f1db2c514c5471e46cc871acf8c9525dd9"]
      },
      "Coverage": {
        "Temporal": {
          "start": ["2024-09-30"],
          "end": ["2024-10-29"]
        },
        "Spatial": ["Part of Great Britain"]
      },
      "ParochialCacheKey": ["f0d480c7d9bf271e4061bfb506d9b931bbc5a79c"]
    },
    {
      "Filename": ["W.tnds.walesish.gtfs.zip"],
      "SizeBytes": [7747839],
      "CreatedAt": ["2024-09-30T05:39:50+0000"],
      "DerivedFrom": {
        "Filename": ["W.bus.tnds.zip"],
        "SizeBytes": [11942185],
        "SourceUrl": ["ftp://ftp.tnds.basemap.co.uk/W.zip"],
        "SourceDownloadedAt": ["2024-09-30T05:37:17+0000"],
        "SourceLicence": ["OGL-UK-3.0"],
        "SourceAttribution": ["Traveline"],
        "ParochialCacheKey": ["f32984214ccbe3e8dcd48bbeb54d42454a26a20b"]
      },
      "Coverage": {
        "Temporal": {
          "start": ["2024-09-30"],
          "end": ["2024-10-29"]
        },
        "Spatial": ["Part of Great Britain"]
      },
      "ParochialCacheKey": ["5ac838d376344d7245a8de595db6c0d16ff63826"]
    },
    {
      "Filename": ["atoc.walesish.gtfs.zip"],
      "SizeBytes": [2051761],
      "CreatedAt": ["2024-09-30T06:25:05+0000"],
      "DerivedFrom": {
        "Filename": ["atoc.zip"],
        "SizeBytes": [70016064],
        "SourceUrl": ["https://data.atoc.org/system/files/ttis237.zip"],
        "SourceDownloadedAt": ["2024-09-30T05:36:40+0000"],
        "SourceLicence": ["CC-BY-2.0"],
        "SourceAttribution": ["RSP Limited (Rail Delivery Group)"],
        "ParochialCacheKey": ["edf1dc2176099c4c6ff0b81f8df28aed8b1c5732"]
      },
      "Coverage": {
        "Temporal": {
          "start": ["2024-09-30"],
          "end": ["2024-10-29"]
        },
        "Spatial": ["Part of Great Britain"]
      },
      "ParochialCacheKey": ["cd41f9d94f19fa090ac8aed1283c0dd31d15643d"]
    },
    {
      "Filename": ["north_west.bods.walesish.gtfs.zip"],
      "SizeBytes": [30927928],
      "CreatedAt": ["2024-09-30T05:37:10+0000"],
      "DerivedFrom": {
        "Filename": ["north_west.bods.gtfs.zip"],
        "SizeBytes": [55755445],
        "SourceUrl": ["https://data.bus-data.dft.gov.uk/timetable/download/gtfs-file/north_west/"],
        "SourceDownloadedAt": ["2024-09-30T05:36:39+0000"],
        "SourceLicence": ["OGL-UK-3.0"],
        "SourceAttribution": ["UK Department for Transport"],
        "ParochialCacheKey": ["826d17adf960291ced3b9165e61a4eb8d730494d"]
      },
      "Coverage": {
        "Temporal": {
          "start": ["2024-09-30"],
          "end": ["2024-10-29"]
        },
        "Spatial": ["Part of Great Britain"]
      },
      "ParochialCacheKey": ["1d38e4125209f6b434001b7755cb53e6b4e4936c"]
    },
    {
      "Filename": ["south_west.bods.walesish.gtfs.zip"],
      "SizeBytes": [23454855],
      "CreatedAt": ["2024-09-30T05:37:55+0000"],
      "DerivedFrom": {
        "Filename": ["south_west.bods.gtfs.zip"],
        "SizeBytes": [104174483],
        "SourceUrl": ["https://data.bus-data.dft.gov.uk/timetable/download/gtfs-file/south_west/"],
        "SourceDownloadedAt": ["2024-09-30T05:37:35+0000"],
        "SourceLicence": ["OGL-UK-3.0"],
        "SourceAttribution": ["UK Department for Transport"],
        "ParochialCacheKey": ["df4efb4d85ad01b79760516ce73fe2f08bb326e8"]
      },
      "Coverage": {
        "Temporal": {
          "start": ["2024-09-30"],
          "end": ["2024-10-29"]
        },
        "Spatial": ["Part of Great Britain"]
      },
      "ParochialCacheKey": ["0a3756110b105ac46cd06f6269108dca9eca0f2a"]
    },
    {
      "Filename": ["west_midlands.bods.walesish.gtfs.zip"],
      "SizeBytes": [13135489],
      "CreatedAt": ["2024-09-30T05:37:30+0000"],
      "DerivedFrom": {
        "Filename": ["west_midlands.bods.gtfs.zip"],
        "SizeBytes": [55358643],
        "SourceUrl": ["https://data.bus-data.dft.gov.uk/timetable/download/gtfs-file/west_midlands/"],
        "SourceDownloadedAt": ["2024-09-30T05:37:14+0000"],
        "SourceLicence": ["OGL-UK-3.0"],
        "SourceAttribution": ["UK Department for Transport"],
        "ParochialCacheKey": ["6b31ed553e1205a09b47afc002961b11608fdccc"]
      },
      "Coverage": {
        "Temporal": {
          "start": ["2024-09-30"],
          "end": ["2024-10-29"]
        },
        "Spatial": ["Part of Great Britain"]
      },
      "ParochialCacheKey": ["2d6cc5b5ae80194e331972fc1e65670bcf5668cd"]
    },
    {
      "Filename": ["walesish.osm.pbf"],
      "SizeBytes": [330845222],
      "CreatedAt": ["2024-09-30T05:41:04+0000"],
      "DerivedFrom": {
        "Filename": ["great-britain-latest.osm.pbf"],
        "SizeBytes": [1814511449],
        "SourceUrl": ["https://download.geofabrik.de/europe/great-britain-latest.osm.pbf"],
        "SourceDownloadedAt": ["2024-09-30T05:38:39+0000"],
        "SourceLicence": ["ODbL-1.0"],
        "SourceAttribution": ["OpenStreetMap contributors"],
        "ParochialCacheKey": ["916f72e4a16ab89093613501e7f21b19babf4b66"]
      },
      "ParochialCacheKey": ["faa26eaf89f4f6de98e7ed1de3987564ed7ebaa6"]
    }
  ],
  "ParochialCacheKey": ["d9bceb45a20858667fcf71b235c3a1b19033a3c0"]
}
