{
  "CreatedAt": "2023-11-20T05:33:24+0000",
  "DerivedFrom": {
    "Filename": "north_west.bods.gtfs.zip",
    "SizeBytes": 51538206,
    "SourceUrl": "https://data.bus-data.dft.gov.uk/timetable/download/gtfs-file/north_west/",
    "SourceDownloadedAt": "2023-11-20T05:32:36+0000",
    "SourceLicence": "OGL-UK-3.0",
    "SourceAttribution": "UK Department for Transport",
    "ParochialCacheKey": "2dd6c81e60b972511540ffb51105dc3b2eddeada"
  },
  "Coverage": {
    "Temporal": {
      "start": "2023-11-20",
      "end": "2023-12-19"
    },
    "Spatial": "Part of Great Britain"
  },
  "ParochialCacheKey": "c72502a53baa89d3f0e19ecc6f47da75a88de0f6"
}
