{
  "CreatedAt": ["2023-08-07T06:02:23+0000"],
  "CreatedWithOpenTripPlannerVersion": ["2.2.0, ser.ver.id: 76, commit: 0e15511b630347df581f1f230de7f470db1b7b26, branch: master"],
  "DerivedFrom": [
    {
      "Filename": ["walesish.osm.pbf"],
      "SizeBytes": [299427987],
      "CreatedAt": ["2023-08-07T05:40:49+0000"],
      "DerivedFrom": {
        "Filename": ["great-britain-latest.osm.pbf"],
        "SizeBytes": [1646759546],
        "SourceUrl": ["https://download.geofabrik.de/europe/great-britain-latest.osm.pbf"],
        "SourceDownloadedAt": ["2023-08-07T05:35:57+0000"],
        "SourceLicence": ["ODbL-1.0"],
        "SourceAttribution": ["OpenStreetMap contributors"],
        "ParochialCacheKey": ["88e640294040df6e59769b40c0910cca9926cf76"]
      },
      "ParochialCacheKey": ["7ae89a0825d407731a4df9ed4f601b01de2bed08"]
    },
    {
      "Filename": ["walesish.terr50.tif"],
      "SizeBytes": [70798519],
      "CreatedAt": ["2023-07-07T11:51:52+0000"],
      "DerivedFrom": {
        "Filename": ["terr50_gagg_gb.zip"],
        "SizeBytes": [161687898],
        "SourceUrl": ["https://api.os.uk/downloads/v1/products/Terrain50/downloads?area=GB&format=ASCII+Grid+and+GML+%28Grid%29&redirect"],
        "SourceDownloadedAt": ["2023-07-07T11:49:11+0000"],
        "SourceLicence": ["OGL-UK-3.0"],
        "SourceAttribution": ["Contains OS data © Crown copyright and database right 2022"],
        "ParochialCacheKey": ["4e0846a2c1d039d5e28346d9431e9afbdcad6e0c"]
      },
      "ParochialCacheKey": ["53231d28014c2a06613084eac16f43420a6520ef"]
    }
  ],
  "ParochialCacheKey": ["5e88e5a162f9d82a64e94f19fa7143eb1a7a1593"]
}
