{
  "CreatedAt": "2023-02-06T05:41:07+0000",
  "DerivedFrom": {
    "Filename": "W.bus.tnds.zip",
    "SizeBytes": 9405006,
    "SourceUrl": "ftp://ftp.tnds.basemap.co.uk/W.zip",
    "SourceDownloadedAt": "2023-02-06T05:32:24+0000",
    "SourceLicence": "OGL-UK-3.0",
    "SourceAttribution": "Traveline",
    "ParochialCacheKey": "abaa1529be0b8b1207676c4957297c22d5a29d82"
  },
  "Coverage": {
    "Temporal": {
      "start": "2023-02-06",
      "end": "2023-03-07"
    },
    "Spatial": "Part of Great Britain"
  },
  "ParochialCacheKey": "b7ca736173cc07ac84dbb7b6995e89215bcddba4"
}
