{
  "CreatedAt": "2023-01-16T05:43:11+0000",
  "DerivedFrom": {
    "Filename": "great-britain-latest.osm.pbf",
    "SizeBytes": 1574644000,
    "SourceUrl": "https://download.geofabrik.de/europe/great-britain-latest.osm.pbf",
    "SourceDownloadedAt": "2023-01-16T05:35:21+0000",
    "SourceLicence": "ODbL-1.0",
    "SourceAttribution": "OpenStreetMap contributors",
    "ParochialCacheKey": "c74083789a99184b78230c81f7cb3feb5092bfb8"
  },
  "ParochialCacheKey": "28351d916a2d8869df61da7cd038a3674e0431ec"
}
